[
    {
        "name":  "Gateway /health responde",
        "expected":  true,
        "actual":  "http://localhost:4000/health",
        "pass":  true
    },
    {
        "name":  "Users-service /api/health responde",
        "expected":  true,
        "actual":  "http://localhost:3020/api/health",
        "pass":  true
    },
    {
        "name":  "Patients-service /health responde",
        "expected":  true,
        "actual":  "http://localhost:3010/health",
        "pass":  true
    },
    {
        "name":  "Login devuelve accessToken",
        "expected":  true,
        "actual":  "[REDACTED]",
        "pass":  true
    },
    {
        "name":  "Perfil /users/me email coincide",
        "expected":  "admin@epem.local",
        "actual":  "admin@epem.local",
        "pass":  true
    },
    {
        "name":  "Listado de pacientes devuelve items",
        "expected":  true,
        "actual":  5,
        "pass":  true
    },
    {
        "name":  "Crear paciente devuelve id",
        "expected":  true,
        "actual":  "85446786-3162-4f68-b675-c2c217a0618a",
        "pass":  true
    },
    {
        "name":  "Patch de paciente actualiza phone",
        "expected":  "11-0000-0000",
        "actual":  "11-0000-0000",
        "pass":  true
    },
    {
        "name":  "Crear paciente duplicado devuelve 409",
        "expected":  409,
        "actual":  409,
        "pass":  true
    },
    {
        "name":  "Catalog-service /health responde",
        "expected":  true,
        "actual":  true,
        "pass":  true
    },
    {
        "name":  "Crear prestación devuelve id",
        "expected":  true,
        "actual":  "ba96e25d-9340-4f63-887c-90a7216577a8",
        "pass":  true
    },
    {
        "name":  "Editar prestación actualiza nombre",
        "expected":  "Prestacion QA Edit",
        "actual":  "Prestacion QA Edit",
        "pass":  true
    },
    {
        "name":  "Crear prestación duplicada devuelve 409",
        "expected":  409,
        "actual":  409,
        "pass":  true
    }
]
