[
  {
    "name": "Gateway /health responde",
    "pass": true,
    "expected": true,
    "actual": "http://localhost:4000/health"
  },
  {
    "name": "Users-service /api/health responde",
    "pass": true,
    "expected": true,
    "actual": "http://localhost:3020/api/health"
  },
  {
    "name": "Patients-service /health responde",
    "pass": false,
    "expected": true,
    "actual": "http://localhost:3010/health"
  },
  {
    "name": "Login devuelve accessToken",
    "pass": true,
    "expected": true,
    "actual": "eyJhbGciOiJIUzI1NiIsInR5cCI6IkpXVCJ9.eyJzdWIiOiI5NGVhYTU1Zi0xMjFjLTQ1MGUtYTdlMi1jNDE1NDA2N2NhMTgiLCJlbWFpbCI6ImFkbWluQGVwZW0ubG9jYWwiLCJyb2xlIjoiQURNSU4iLCJpYXQiOjE3NjEzMzk4MTUsImV4cCI6MTc2MTM0MDcxNX0.pdoPRBuj2AjL_IZuggzgkg8dXrz4jzVUB4LCYwhSPQA"
  },
  {
    "name": "Perfil /users/me email coincide",
    "pass": true,
    "expected": "admin@epem.local",
    "actual": "admin@epem.local"
  },
  {
    "name": "Listado de pacientes devuelve items",
    "pass": false,
    "expected": true,
    "actual": "status=500"
  },
  {
    "name": "Crear paciente devuelve id",
    "pass": false,
    "expected": true,
    "actual": "status=500"
  },
  {
    "name": "Crear paciente duplicado devuelve 409",
    "pass": false,
    "expected": 409,
    "actual": 500
  },
  {
    "name": "Catalog-service /health responde",
    "pass": false,
    "expected": true,
    "actual": false
  }
]